{
  "source": "experiment-runner metrics rows",
  "confusion_matrix_layout": "[[TN, FP], [FN, TP]]",
  "selection_rule": "selected_threshold maximizes validation F1 and is then applied to test data",
  "experiments": {
    "AB_C1_FEDAVG_TCN": {
      "experiment_id": "AB_C1_FEDAVG_TCN",
      "seed": null,
      "cluster_id": 1,
      "dataset": "HAI 21.03",
      "run_category": "ablation_fl_method",
      "model_family": "tcn",
      "fl_method": "FedAvg",
      "aggregation": "weighted_arithmetic_mean",
      "threshold_selected_on": "validation",
      "selected_threshold": 0.8067960739135742,
      "default_threshold": 0.5,
      "status": "complete",
      "tuned_threshold": {
        "tn": 24503,
        "fp": 21,
        "fn": 150,
        "tp": 106,
        "matrix": [
          [
            24503,
            21
          ],
          [
            150,
            106
          ]
        ]
      },
      "default_threshold_metrics": {
        "tn": 24483,
        "fp": 41,
        "fn": 134,
        "tp": 122,
        "matrix": [
          [
            24483,
            41
          ],
          [
            134,
            122
          ]
        ]
      }
    },
    "AB_C2_FEDAVG_MLP": {
      "experiment_id": "AB_C2_FEDAVG_MLP",
      "seed": null,
      "cluster_id": 2,
      "dataset": "TON IoT combined telemetry",
      "run_category": "ablation_fl_method",
      "model_family": "compact_mlp",
      "fl_method": "FedAvg",
      "aggregation": "weighted_arithmetic_mean",
      "threshold_selected_on": "validation",
      "selected_threshold": 0.8570539951324463,
      "default_threshold": 0.5,
      "status": "complete",
      "tuned_threshold": {
        "tn": 4119,
        "fp": 1806,
        "fn": 0,
        "tp": 11850,
        "matrix": [
          [
            4119,
            1806
          ],
          [
            0,
            11850
          ]
        ]
      },
      "default_threshold_metrics": {
        "tn": 0,
        "fp": 5925,
        "fn": 0,
        "tp": 11850,
        "matrix": [
          [
            0,
            5925
          ],
          [
            0,
            11850
          ]
        ]
      }
    },
    "AB_C3_FEDAVG_CNN1D": {
      "experiment_id": "AB_C3_FEDAVG_CNN1D",
      "seed": null,
      "cluster_id": 3,
      "dataset": "WUSTL-IIOT-2021",
      "run_category": "ablation_fl_method",
      "model_family": "cnn1d",
      "fl_method": "FedAvg",
      "aggregation": "weighted_arithmetic_mean",
      "threshold_selected_on": "validation",
      "selected_threshold": 0.009300285018980503,
      "default_threshold": 0.5,
      "status": "complete",
      "tuned_threshold": {
        "tn": 156628,
        "fp": 5016,
        "fn": 137,
        "tp": 17394,
        "matrix": [
          [
            156628,
            5016
          ],
          [
            137,
            17394
          ]
        ]
      },
      "default_threshold_metrics": {
        "tn": 160627,
        "fp": 1017,
        "fn": 17502,
        "tp": 29,
        "matrix": [
          [
            160627,
            1017
          ],
          [
            17502,
            29
          ]
        ]
      }
    }
  }
}
