{
  "source": "experiment-runner metrics rows",
  "confusion_matrix_layout": "[[TN, FP], [FN, TP]]",
  "selection_rule": "selected_threshold maximizes validation F1 and is then applied to test data",
  "experiments": {
    "A_C1": {
      "experiment_id": "A_C1",
      "seed": null,
      "cluster_id": 1,
      "dataset": "HAI 21.03",
      "run_category": "baseline_flat",
      "model_family": "cnn1d",
      "fl_method": "FedAvg",
      "aggregation": "weighted_arithmetic_mean",
      "threshold_selected_on": "validation",
      "selected_threshold": 0.9642142653465271,
      "default_threshold": 0.5,
      "status": "complete",
      "tuned_threshold": {
        "tn": 24514,
        "fp": 10,
        "fn": 152,
        "tp": 104,
        "matrix": [
          [
            24514,
            10
          ],
          [
            152,
            104
          ]
        ]
      },
      "default_threshold_metrics": {
        "tn": 24459,
        "fp": 65,
        "fn": 132,
        "tp": 124,
        "matrix": [
          [
            24459,
            65
          ],
          [
            132,
            124
          ]
        ]
      }
    },
    "A_C2": {
      "experiment_id": "A_C2",
      "seed": null,
      "cluster_id": 2,
      "dataset": "TON IoT combined telemetry",
      "run_category": "baseline_flat",
      "model_family": "cnn1d",
      "fl_method": "FedAvg",
      "aggregation": "weighted_arithmetic_mean",
      "threshold_selected_on": "validation",
      "selected_threshold": 0.5080185532569885,
      "default_threshold": 0.5,
      "status": "complete",
      "tuned_threshold": {
        "tn": 4148,
        "fp": 1777,
        "fn": 88,
        "tp": 11762,
        "matrix": [
          [
            4148,
            1777
          ],
          [
            88,
            11762
          ]
        ]
      },
      "default_threshold_metrics": {
        "tn": 0,
        "fp": 5925,
        "fn": 0,
        "tp": 11850,
        "matrix": [
          [
            0,
            5925
          ],
          [
            0,
            11850
          ]
        ]
      }
    },
    "A_C3": {
      "experiment_id": "A_C3",
      "seed": null,
      "cluster_id": 3,
      "dataset": "WUSTL-IIOT-2021",
      "run_category": "baseline_flat",
      "model_family": "cnn1d",
      "fl_method": "FedAvg",
      "aggregation": "weighted_arithmetic_mean",
      "threshold_selected_on": "validation",
      "selected_threshold": 0.007514748256653547,
      "default_threshold": 0.5,
      "status": "complete",
      "tuned_threshold": {
        "tn": 156627,
        "fp": 5017,
        "fn": 165,
        "tp": 17366,
        "matrix": [
          [
            156627,
            5017
          ],
          [
            165,
            17366
          ]
        ]
      },
      "default_threshold_metrics": {
        "tn": 160667,
        "fp": 977,
        "fn": 17474,
        "tp": 57,
        "matrix": [
          [
            160667,
            977
          ],
          [
            17474,
            57
          ]
        ]
      }
    },
    "B_C1": {
      "experiment_id": "B_C1",
      "seed": null,
      "cluster_id": 1,
      "dataset": "HAI 21.03",
      "run_category": "baseline_uniform_hierarchical",
      "model_family": "cnn1d",
      "fl_method": "FedAvg",
      "aggregation": "weighted_arithmetic_mean",
      "threshold_selected_on": "validation",
      "selected_threshold": 0.9632313847541809,
      "default_threshold": 0.5,
      "status": "complete",
      "tuned_threshold": {
        "tn": 24514,
        "fp": 10,
        "fn": 152,
        "tp": 104,
        "matrix": [
          [
            24514,
            10
          ],
          [
            152,
            104
          ]
        ]
      },
      "default_threshold_metrics": {
        "tn": 24460,
        "fp": 64,
        "fn": 131,
        "tp": 125,
        "matrix": [
          [
            24460,
            64
          ],
          [
            131,
            125
          ]
        ]
      }
    },
    "B_C2": {
      "experiment_id": "B_C2",
      "seed": null,
      "cluster_id": 2,
      "dataset": "TON IoT combined telemetry",
      "run_category": "baseline_uniform_hierarchical",
      "model_family": "cnn1d",
      "fl_method": "FedAvg",
      "aggregation": "weighted_arithmetic_mean",
      "threshold_selected_on": "validation",
      "selected_threshold": 0.5080230236053467,
      "default_threshold": 0.5,
      "status": "complete",
      "tuned_threshold": {
        "tn": 4148,
        "fp": 1777,
        "fn": 88,
        "tp": 11762,
        "matrix": [
          [
            4148,
            1777
          ],
          [
            88,
            11762
          ]
        ]
      },
      "default_threshold_metrics": {
        "tn": 0,
        "fp": 5925,
        "fn": 0,
        "tp": 11850,
        "matrix": [
          [
            0,
            5925
          ],
          [
            0,
            11850
          ]
        ]
      }
    },
    "B_C3": {
      "experiment_id": "B_C3",
      "seed": null,
      "cluster_id": 3,
      "dataset": "WUSTL-IIOT-2021",
      "run_category": "baseline_uniform_hierarchical",
      "model_family": "cnn1d",
      "fl_method": "FedAvg",
      "aggregation": "weighted_arithmetic_mean",
      "threshold_selected_on": "validation",
      "selected_threshold": 0.009300285018980503,
      "default_threshold": 0.5,
      "status": "complete",
      "tuned_threshold": {
        "tn": 156628,
        "fp": 5016,
        "fn": 137,
        "tp": 17394,
        "matrix": [
          [
            156628,
            5016
          ],
          [
            137,
            17394
          ]
        ]
      },
      "default_threshold_metrics": {
        "tn": 160627,
        "fp": 1017,
        "fn": 17502,
        "tp": 29,
        "matrix": [
          [
            160627,
            1017
          ],
          [
            17502,
            29
          ]
        ]
      }
    },
    "P_C1": {
      "experiment_id": "P_C1",
      "seed": null,
      "cluster_id": 1,
      "dataset": "HAI 21.03",
      "run_category": "proposed_specialized_hierarchical",
      "model_family": "tcn",
      "fl_method": "FedBN",
      "aggregation": "weighted_non_bn_mean",
      "threshold_selected_on": "validation",
      "selected_threshold": 0.9929866194725037,
      "default_threshold": 0.5,
      "status": "complete",
      "tuned_threshold": {
        "tn": 24505,
        "fp": 19,
        "fn": 166,
        "tp": 90,
        "matrix": [
          [
            24505,
            19
          ],
          [
            166,
            90
          ]
        ]
      },
      "default_threshold_metrics": {
        "tn": 22919,
        "fp": 1605,
        "fn": 114,
        "tp": 142,
        "matrix": [
          [
            22919,
            1605
          ],
          [
            114,
            142
          ]
        ]
      }
    },
    "P_C2": {
      "experiment_id": "P_C2",
      "seed": null,
      "cluster_id": 2,
      "dataset": "TON IoT combined telemetry",
      "run_category": "proposed_specialized_hierarchical",
      "model_family": "compact_mlp",
      "fl_method": "FedProx",
      "aggregation": "weighted_arithmetic_mean",
      "threshold_selected_on": "validation",
      "selected_threshold": 0.637915849685669,
      "default_threshold": 0.5,
      "status": "complete",
      "tuned_threshold": {
        "tn": 4121,
        "fp": 1804,
        "fn": 0,
        "tp": 11850,
        "matrix": [
          [
            4121,
            1804
          ],
          [
            0,
            11850
          ]
        ]
      },
      "default_threshold_metrics": {
        "tn": 2370,
        "fp": 3555,
        "fn": 0,
        "tp": 11850,
        "matrix": [
          [
            2370,
            3555
          ],
          [
            0,
            11850
          ]
        ]
      }
    },
    "P_C3": {
      "experiment_id": "P_C3",
      "seed": null,
      "cluster_id": 3,
      "dataset": "WUSTL-IIOT-2021",
      "run_category": "proposed_specialized_hierarchical",
      "model_family": "cnn1d",
      "fl_method": "SCAFFOLD",
      "aggregation": "weighted_arithmetic_mean",
      "threshold_selected_on": "validation",
      "selected_threshold": 0.13174223899841309,
      "default_threshold": 0.5,
      "status": "complete",
      "tuned_threshold": {
        "tn": 156468,
        "fp": 5176,
        "fn": 61,
        "tp": 17470,
        "matrix": [
          [
            156468,
            5176
          ],
          [
            61,
            17470
          ]
        ]
      },
      "default_threshold_metrics": {
        "tn": 156975,
        "fp": 4669,
        "fn": 2024,
        "tp": 15507,
        "matrix": [
          [
            156975,
            4669
          ],
          [
            2024,
            15507
          ]
        ]
      }
    },
    "AB_C1_FEDAVG_TCN": {
      "experiment_id": "AB_C1_FEDAVG_TCN",
      "seed": null,
      "cluster_id": 1,
      "dataset": "HAI 21.03",
      "run_category": "ablation_fl_method",
      "model_family": "tcn",
      "fl_method": "FedAvg",
      "aggregation": "weighted_arithmetic_mean",
      "threshold_selected_on": "validation",
      "selected_threshold": 0.8067960739135742,
      "default_threshold": 0.5,
      "status": "complete",
      "tuned_threshold": {
        "tn": 24503,
        "fp": 21,
        "fn": 150,
        "tp": 106,
        "matrix": [
          [
            24503,
            21
          ],
          [
            150,
            106
          ]
        ]
      },
      "default_threshold_metrics": {
        "tn": 24483,
        "fp": 41,
        "fn": 134,
        "tp": 122,
        "matrix": [
          [
            24483,
            41
          ],
          [
            134,
            122
          ]
        ]
      }
    },
    "AB_C2_FEDAVG_MLP": {
      "experiment_id": "AB_C2_FEDAVG_MLP",
      "seed": null,
      "cluster_id": 2,
      "dataset": "TON IoT combined telemetry",
      "run_category": "ablation_fl_method",
      "model_family": "compact_mlp",
      "fl_method": "FedAvg",
      "aggregation": "weighted_arithmetic_mean",
      "threshold_selected_on": "validation",
      "selected_threshold": 0.8570539951324463,
      "default_threshold": 0.5,
      "status": "complete",
      "tuned_threshold": {
        "tn": 4119,
        "fp": 1806,
        "fn": 0,
        "tp": 11850,
        "matrix": [
          [
            4119,
            1806
          ],
          [
            0,
            11850
          ]
        ]
      },
      "default_threshold_metrics": {
        "tn": 0,
        "fp": 5925,
        "fn": 0,
        "tp": 11850,
        "matrix": [
          [
            0,
            5925
          ],
          [
            0,
            11850
          ]
        ]
      }
    },
    "AB_C3_FEDAVG_CNN1D": {
      "experiment_id": "AB_C3_FEDAVG_CNN1D",
      "seed": null,
      "cluster_id": 3,
      "dataset": "WUSTL-IIOT-2021",
      "run_category": "ablation_fl_method",
      "model_family": "cnn1d",
      "fl_method": "FedAvg",
      "aggregation": "weighted_arithmetic_mean",
      "threshold_selected_on": "validation",
      "selected_threshold": 0.009300285018980503,
      "default_threshold": 0.5,
      "status": "complete",
      "tuned_threshold": {
        "tn": 156628,
        "fp": 5016,
        "fn": 137,
        "tp": 17394,
        "matrix": [
          [
            156628,
            5016
          ],
          [
            137,
            17394
          ]
        ]
      },
      "default_threshold_metrics": {
        "tn": 160627,
        "fp": 1017,
        "fn": 17502,
        "tp": 29,
        "matrix": [
          [
            160627,
            1017
          ],
          [
            17502,
            29
          ]
        ]
      }
    }
  }
}
